<?xml version="1.0" encoding="UTF-8" ?>
<viper xmlns="http://lamp.cfar.umd.edu/viper#" xmlns:data="http://lamp.cfar.umd.edu/viperdata#">
<config>
<descriptor name="Information" type="FILE">
<attribute dynamic="false" name="SOURCETYPE" type="http://lamp.cfar.umd.edu/viperdata#lvalue">
<data:lvalue-possibles>
<data:lvalue-enum value="SEQUENCE" /> 
<data:lvalue-enum value="FRAMES" /> 
</data:lvalue-possibles>
</attribute>
<attribute dynamic="false" name="NUMFRAMES" type="http://lamp.cfar.umd.edu/viperdata#dvalue" /> 
<attribute dynamic="false" name="FRAMERATE" type="http://lamp.cfar.umd.edu/viperdata#fvalue" /> 
<attribute dynamic="false" name="H-FRAME-SIZE" type="http://lamp.cfar.umd.edu/viperdata#dvalue" /> 
<attribute dynamic="false" name="V-FRAME-SIZE" type="http://lamp.cfar.umd.edu/viperdata#dvalue" /> 
</descriptor>
<descriptor name="PutObject" type="OBJECT">
<attribute dynamic="false" name="BoundingBox" type="http://lamp.cfar.umd.edu/viperdata#bbox" /> 
</descriptor>
<descriptor name="AbandonedObject" type="OBJECT">
<attribute dynamic="false" name="BoundingBox" type="http://lamp.cfar.umd.edu/viperdata#bbox" /> 
</descriptor>
<descriptor name="StolenObject" type="OBJECT">
<attribute dynamic="false" name="BoundingBox" type="http://lamp.cfar.umd.edu/viperdata#bbox" /> 
</descriptor>
<descriptor name="AbandonedPerson" type="OBJECT">
<attribute dynamic="false" name="BoundingBox" type="http://lamp.cfar.umd.edu/viperdata#bbox" /> 
</descriptor>
<descriptor name="StolenPerson" type="OBJECT">
<attribute dynamic="false" name="BoundingBox" type="http://lamp.cfar.umd.edu/viperdata#bbox" /> 
</descriptor>
</config>
<data>
<sourcefile filename="">
<file id="0" name="Information">
<attribute name="SOURCETYPE"> 
<data:lvalue value="SEQUENCE"/> 
</attribute>
<attribute name="NUMFRAMES">
<data:dvalue value="3051" /> 
</attribute>
<attribute name="FRAMERATE">
<data:fvalue value="30.0" /> 
</attribute>
<attribute name="H-FRAME-SIZE" > 
<data:dvalue value="720" /> 
</attribute>
<attribute name="V-FRAME-SIZE" > 
<data:dvalue value="576" /> 
</attribute>
</file>
<object framespan="1058:2100" id="0" name="AbandonedObject">
<attribute name="BoundingBox">
<data:bbox height="22" width="13" x="288" y="130"/> 
</attribute>
</object>
<object framespan="1174:2183" id="2" name="AbandonedObject">
<attribute name="BoundingBox">
<data:bbox height="41" width="17" x="495" y="130"/> 
</attribute>
</object>
<object framespan="1355:2357" id="6" name="AbandonedObject">
<attribute name="BoundingBox">
<data:bbox height="9" width="8" x="643" y="99"/> 
</attribute>
</object>
<object framespan="1356:2359" id="7" name="AbandonedObject">
<attribute name="BoundingBox">
<data:bbox height="48" width="8" x="643" y="109"/> 
</attribute>
</object>
<object framespan="1356:2360" id="8" name="AbandonedObject">
<attribute name="BoundingBox">
<data:bbox height="26" width="8" x="640" y="157"/> 
</attribute>
</object>
<object framespan="1358:2361" id="9" name="AbandonedObject">
<attribute name="BoundingBox">
<data:bbox height="5" width="7" x="643" y="110"/> 
</attribute>
</object>
<object framespan="1356:2364" id="6" name="AbandonedObject">
<attribute name="BoundingBox">
<data:bbox height="62" width="10" x="644" y="37"/> 
</attribute>
</object>
<object framespan="1322:3053" id="4" name="StolenObject">
<attribute name="BoundingBox">
<data:bbox height="16" width="10" x="700" y="29"/> 
</attribute>
</object>
<object framespan="2069:3053" id="9" name="AbandonedObject">
<attribute name="BoundingBox">
<data:bbox height="42" width="28" x="481" y="189"/> 
</attribute>
</object>
<object framespan="2073:3053" id="10" name="AbandonedObject">
<attribute name="BoundingBox">
<data:bbox height="29" width="18" x="47" y="129"/> 
</attribute>
</object>
<object framespan="2191:3053" id="11" name="AbandonedObject">
<attribute name="BoundingBox">
<data:bbox height="28" width="13" x="289" y="125"/> 
</attribute>
</object>
</sourcefile>
</data>
</viper>
